{
  "variants": {
    "layers=1": {
      "model": "ironstars:block/moon_dust/2"
    },
    "layers=2": {
      "model": "ironstars:block/moon_dust/4"
    },
    "layers=3": {
      "model": "ironstars:block/moon_dust/6"
    },
    "layers=4": {
      "model": "ironstars:block/moon_dust/8"
    },
    "layers=5": {
      "model": "ironstars:block/moon_dust/10"
    },
    "layers=6": {
      "model": "ironstars:block/moon_dust/12"
    },
    "layers=7": {
      "model": "ironstars:block/moon_dust/14"
    },
    "layers=8": {
      "model": "ironstars:block/moon_dust/16"
    }
  }
}